<?xml version="1.0" encoding="UTF-8"?>
<!DOCTYPE suite SYSTEM "https://testng.org/testng-1.0.dtd">
<suite name="GroupExecutionSuite" thread-count="3">

  <!-- ✅ Define listener once at suite level -->
  <listeners>
    <listener class-name="Utilities.ExtentReportManager"/>
  </listeners> 
  
  <test thread-count="5" name="Test">
  
  	<groups>
  		<run>
  			<include name="Master"></include>
  		</run>
  	</groups>
  
    <classes>
       	<class name="Expenses_Test.Expenses_FullTest"/>
    </classes>
    
  </test> <!-- Test -->
</suite> <!-- Suite -->
